whmcs_api_client-1.0.13.dist-info/licenses/LICENSE
whmcs_client/__init__.py
whmcs_client/api_client.py
whmcs_client/api_response.py
whmcs_client/configuration.py
whmcs_client/exceptions.py
whmcs_client/py.typed
whmcs_client/rest.py
whmcs_client/api/__init__.py
whmcs_client/api/default_api.py
whmcs_client/models/__init__.py
whmcs_client/models/add_client_response.py
whmcs_client/models/add_client_response_all_of_clientid.py
whmcs_client/models/add_order_request_clientid.py
whmcs_client/models/add_order_response.py
whmcs_client/models/client_info.py
whmcs_client/models/currency_info.py
whmcs_client/models/get_clients_response.py
whmcs_client/models/get_clients_response_all_of_clients.py
whmcs_client/models/get_currencies_response.py
whmcs_client/models/get_currencies_response_all_of_currencies.py
whmcs_client/models/update_client_request_clientid.py
whmcs_client/models/update_client_response.py
whmcs_client/models/update_client_response_all_of_clientid.py
whmcs_client/models/whmcs_base_response.py
whmcs_client/models/whmcs_error_response.py
whmcs_client/models/whmcs_success_response.py
whmcs_api_client-1.0.13.dist-info/METADATA
whmcs_api_client-1.0.13.dist-info/WHEEL
whmcs_api_client-1.0.13.dist-info/top_level.txt
whmcs_api_client-1.0.13.dist-info/RECORD
